patcherex2/__init__.py
patcherex2/patcherex.py
patcherex2/components/allocation_managers/__init__.py
patcherex2/components/allocation_managers/allocation_manager.py
patcherex2/components/archinfo/__init__.py
patcherex2/components/archinfo/aarch64.py
patcherex2/components/archinfo/amd64.py
patcherex2/components/archinfo/arm.py
patcherex2/components/archinfo/mips.py
patcherex2/components/archinfo/mips64.py
patcherex2/components/archinfo/ppc.py
patcherex2/components/archinfo/ppc64.py
patcherex2/components/archinfo/ppc_vle.py
patcherex2/components/archinfo/s390x.py
patcherex2/components/archinfo/sparc.py
patcherex2/components/archinfo/x86.py
patcherex2/components/assemblers/__init__.py
patcherex2/components/assemblers/assembler.py
patcherex2/components/assemblers/bcc.py
patcherex2/components/assemblers/keystone.py
patcherex2/components/assemblers/keystone_arm.py
patcherex2/components/assemblers/keystone_sparc.py
patcherex2/components/assemblers/ppc_vle.py
patcherex2/components/assets/.gitignore
patcherex2/components/assets/assets.py
patcherex2/components/binary_analyzers/__init__.py
patcherex2/components/binary_analyzers/angr.py
patcherex2/components/binary_analyzers/binary_analyzer.py
patcherex2/components/binary_analyzers/ghidra.py
patcherex2/components/binary_analyzers/ida.py
patcherex2/components/binfmt_tools/__init__.py
patcherex2/components/binfmt_tools/binary.py
patcherex2/components/binfmt_tools/binfmt_tool.py
patcherex2/components/binfmt_tools/elf.py
patcherex2/components/binfmt_tools/ihex.py
patcherex2/components/compilers/__init__.py
patcherex2/components/compilers/bcc.py
patcherex2/components/compilers/clang.py
patcherex2/components/compilers/clang_arm.py
patcherex2/components/compilers/compiler.py
patcherex2/components/compilers/llvm_recomp.py
patcherex2/components/compilers/llvm_recomp_arm.py
patcherex2/components/compilers/ppc_vle.py
patcherex2/components/disassemblers/__init__.py
patcherex2/components/disassemblers/capstone.py
patcherex2-0.2.9.dist-info/licenses/LICENSE
patcherex2-0.2.9.dist-info/METADATA
patcherex2-0.2.9.dist-info/WHEEL
patcherex2-0.2.9.dist-info/top_level.txt
patcherex2-0.2.9.dist-info/RECORD
