Metadata-Version: 2.4
Name: patcherex2
Version: 0.2.9
Project-URL: Homepage, https://github.com/purseclab/Patcherex2
Project-URL: Source, https://github.com/purseclab/Patcherex2
Project-URL: Tracker, https://github.com/purseclab/Patcherex2/issues
Requires-Python: >=3.8
License-File: LICENSE
Requires-Dist: angr
Requires-Dist: pyelftools
Requires-Dist: pypcode
Requires-Dist: lief
Requires-Dist: keystone-engine
Requires-Dist: intelhex
Requires-Dist: requests
Provides-Extra: ghidra
Requires-Dist: pyhidra; extra == "ghidra"
Provides-Extra: all
Requires-Dist: patcherex2[ghidra]; extra == "all"
Dynamic: license-file
